LICENSE
MANIFEST.in
README.md
setup.py
qrequest/__init__.py
qrequest/database.py
qrequest/main.py
qrequest/webserver.py
qrequest.egg-info/PKG-INFO
qrequest.egg-info/SOURCES.txt
qrequest.egg-info/dependency_links.txt
qrequest.egg-info/entry_points.txt
qrequest.egg-info/not-zip-safe
qrequest.egg-info/requires.txt
qrequest.egg-info/top_level.txt
static/superhero.bootstrap.min.css
templates/index.html
templates/results.html
templates/setup_query.html