Metadata-Version: 1.0
Name: qrequest
Version: 0.1.7
Summary: Instantly create an API and web interface for SQL queries.
Home-page: https://github.com/benjamin-croker/qrequest
Author: Benjamin Croker
Author-email: benjamin.croker@gmail.com
License: GNU GENERAL PUBLIC LICENSE
